{
  "parent": "minecraft:recipes/root",
  "rewards": {
    "recipes": [
      "uc:chiseled_polished_blackstone_cdrb_un"
    ]
  },
  "criteria": {
    "has_uc:compressed_chiseled_polished_blackstone": {
      "trigger": "minecraft:inventory_changed",
      "conditions": {
        "items": [
          {
            "items": [
              "uc:compressed_chiseled_polished_blackstone"
            ]
          }
        ]
      }
    },
    "has_the_recipe": {
      "trigger": "minecraft:recipe_unlocked",
      "conditions": {
        "recipe": "uc:chiseled_polished_blackstone_cdrb_un"
      }
    }
  },
  "requirements": [
    [
      "has_uc:compressed_chiseled_polished_blackstone",
      "has_the_recipe"
    ]
  ]
}