{
  "parent": "minecraft:recipes/root",
  "rewards": {
    "recipes": [
      "uc_minecraft:cobblestone"
    ]
  },
  "criteria": {
    "has_minecraft:cobblestone": {
      "trigger": "minecraft:inventory_changed",
      "conditions": {
        "items": [
          {
            "items": [
              "uc:compressed_cobblestone"
            ]
          }
        ]
      }
    },
    "has_the_recipe": {
      "trigger": "minecraft:recipe_unlocked",
      "conditions": {
        "recipe": "uc_minecraft:cobblestone"
      }
    }
  },
  "requirements": [
    [
      "has_minecraft:cobblestone",
      "has_the_recipe"
    ]
  ]
}