{
  "parent": "minecraft:recipes/root",
  "rewards": {
    "recipes": [
      "uc_minecraft:soul_soil"
    ]
  },
  "criteria": {
    "has_minecraft:soul_soil": {
      "trigger": "minecraft:inventory_changed",
      "conditions": {
        "items": [
          {
            "items": [
              "uc:compressed_soul_soil"
            ]
          }
        ]
      }
    },
    "has_the_recipe": {
      "trigger": "minecraft:recipe_unlocked",
      "conditions": {
        "recipe": "uc_minecraft:soul_soil"
      }
    }
  },
  "requirements": [
    [
      "has_minecraft:soul_soil",
      "has_the_recipe"
    ]
  ]
}