{
  "parent": "minecraft:recipes/root",
  "rewards": {
    "recipes": [
      "uc_material_uc:compressed_emerald_gem"
    ]
  },
  "criteria": {
    "has_minecraft:emerald": {
      "trigger": "minecraft:inventory_changed",
      "conditions": {
        "items": [
          {
            "items": [
              "minecraft:emerald"
            ]
          }
        ]
      }
    },
    "has_the_recipe": {
      "trigger": "minecraft:recipe_unlocked",
      "conditions": {
        "recipe": "uc_material_uc:compressed_emerald_gem"
      }
    }
  },
  "requirements": [
    [
      "has_minecraft:emerald",
      "has_the_recipe"
    ]
  ]
}