{
  "parent": "minecraft:recipes/root",
  "rewards": {
    "recipes": [
      "uc:compressed_crimson_nylium_cdrb"
    ]
  },
  "criteria": {
    "has_minecraft:crimson_nylium": {
      "trigger": "minecraft:inventory_changed",
      "conditions": {
        "items": [
          {
            "items": [
              "minecraft:crimson_nylium"
            ]
          }
        ]
      }
    },
    "has_the_recipe": {
      "trigger": "minecraft:recipe_unlocked",
      "conditions": {
        "recipe": "uc:compressed_crimson_nylium_cdrb"
      }
    }
  },
  "requirements": [
    [
      "has_minecraft:crimson_nylium",
      "has_the_recipe"
    ]
  ]
}