{
  "parent": "minecraft:recipes/root",
  "rewards": {
    "recipes": [
      "uc:compressed_rabbit_smoking"
    ]
  },
  "criteria": {
    "has_smoking_compressed_rabbit": {
      "trigger": "minecraft:inventory_changed",
      "conditions": {
        "items": [
          {
            "items": [
              "uc:compressed_rabbit"
            ]
          }
        ]
      }
    },
    "has_the_recipe": {
      "trigger": "minecraft:recipe_unlocked",
      "conditions": {
        "recipe": "uc:compressed_rabbit_smoking"
      }
    }
  },
  "requirements": [
    [
      "has_smoking_compressed_rabbit",
      "has_the_recipe"
    ]
  ]
}